[
  {
    "id": "ba0b6a5c-6abb-4eaa-bfca-d3ede7b5d5ae",
    "data": [
      {
        "text": "Selling",
        "userDefined": false
      }
    ],
    "isTemplate": false,
    "count": 0
  },
  {
    "id": "1e9a61d9-8e71-42ec-989d-92b60df49bcb",
    "data": [
      {
        "text": "I want to sell",
        "userDefined": false
      }
    ],
    "isTemplate": false,
    "count": 0
  },
  {
    "id": "f3efd3ac-473e-497f-b0a7-0e7b3a85e957",
    "data": [
      {
        "text": "Sell",
        "userDefined": false
      }
    ],
    "isTemplate": false,
    "count": 0,
    "updated": 1510626321
  },
  {
    "id": "adcf01ac-6b83-4adb-8664-ce66d6fb773a",
    "data": [
      {
        "text": "I want sell",
        "userDefined": false
      }
    ],
    "isTemplate": false,
    "count": 1
  }
]